{
    "type": "minecraft:crafting_shaped",
    
    "pattern":
    [
        "EGE",
        "GBG",
        "EGE"      
    ],
    
    "key":
    {
        "E":
        {
            "tag": "forge:gems/endonium_crystal"
        },
        "B":
        {
            "item": "mechanicraft_revived:supreme_fluid_tank"
        },
        "G":
        {
            "tag": "forge:glass_panes"
        }
    },
    
    "result":
    {
        "item": "mechanicraft_revived:ultimate_fluid_tank",
        "count": 1
    }
}